dict_merger_keep_all/LICENSE
dict_merger_keep_all/README.MD
dict_merger_keep_all/__init__.py
dict_merger_keep_all/requirements.txt
dict_merger_keep_all/thirdparty.json
dict_merger_keep_all-0.10.dist-info/LICENSE.rst
dict_merger_keep_all-0.10.dist-info/METADATA
dict_merger_keep_all-0.10.dist-info/WHEEL
dict_merger_keep_all-0.10.dist-info/top_level.txt
dict_merger_keep_all-0.10.dist-info/RECORD
